{
  "offense_summary": {
    "subject": {
      "eligible": "offense",
      "grade_keys": [
        "offense",
        "offense_penalty",
        "hands_fumble",
        "screen_block",
        "run",
        "pass_block",
        "run_block",
        "pass_route",
        "pass",
        "snap"
      ],
      "league_id": 2,
      "player_id": 172865,
      "roster": "offense",
      "season": 2025,
      "secondary": false,
      "week": [
        "0",
        "1",
        "2",
        "3",
        "4",
        "5",
        "6",
        "7",
        "8",
        "9",
        "10",
        "11",
        "12",
        "13",
        "14",
        "15",
        "16",
        "17",
        "18",
        "19",
        "20"
      ]
    },
    "week_totals": [
      {
        "declined_penalties": 0,
        "franchise_id": 308,
        "grades_offense": 50.9,
        "grades_offense_penalty": 84,
        "grades_pass_block": 37.2,
        "grades_run_block": 51.2,
        "league_id": 2,
        "penalties": 0,
        "player_game_count": 8,
        "season": 2025,
        "season_id": 2025,
        "snap_counts_pass": 0,
        "snap_counts_pass_block": 127,
        "snap_counts_pass_route": 0,
        "snap_counts_run": 0,
        "snap_counts_run_block": 65,
        "snap_counts_total": 192,
        "snap_counts_total_pass": 127,
        "snap_counts_total_run": 65,
        "team_name": "TENN STATE"
      }
    ],
    "weeks": [
      {
        "away_franchise_id": 250,
        "away_team_name": "NDSTAT",
        "declined_penalties": 0,
        "game": {
          "away_franchise_id": 250,
          "away_team_name": "NDSTAT",
          "game_id": 29677,
          "home_franchise_id": 308,
          "home_team_name": "TENNST",
          "player_franchise_id": 308,
          "position": "LG",
          "status": "P",
          "week": 2
        },
        "game_id": 29677,
        "grades_offense": 54.6,
        "grades_offense_penalty": 69.8,
        "grades_pass_block": 73.5,
        "grades_run_block": 56.4,
        "home_franchise_id": 308,
        "home_team_name": "TENNST",
        "jersey_number": "69",
        "penalties": 0,
        "player_franchise_id": 308,
        "player_id": 172865,
        "position": "LG",
        "snap_counts_pass": 0,
        "snap_counts_pass_block": 2,
        "snap_counts_pass_route": 0,
        "snap_counts_run": 0,
        "snap_counts_run_block": 2,
        "snap_counts_total": 4,
        "snap_counts_total_pass": 2,
        "snap_counts_total_run": 2,
        "status": "P",
        "week": 2
      },
      {
        "away_franchise_id": 104,
        "away_team_name": "ALABAM",
        "declined_penalties": 0,
        "game": {
          "away_franchise_id": 104,
          "away_team_name": "ALABAM",
          "game_id": 29745,
          "home_franchise_id": 308,
          "home_team_name": "TENNST",
          "player_franchise_id": 308,
          "position": "LG",
          "status": "P",
          "week": 3
        },
        "game_id": 29745,
        "grades_offense": 55.8,
        "grades_offense_penalty": 70.6,
        "grades_pass_block": 19.5,
        "grades_run_block": 59.3,
        "home_franchise_id": 308,
        "home_team_name": "TENNST",
        "jersey_number": "69",
        "penalties": 0,
        "player_franchise_id": 308,
        "player_id": 172865,
        "position": "LG",
        "snap_counts_pass": 0,
        "snap_counts_pass_block": 3,
        "snap_counts_pass_route": 0,
        "snap_counts_run": 0,
        "snap_counts_run_block": 2,
        "snap_counts_total": 5,
        "snap_counts_total_pass": 3,
        "snap_counts_total_run": 2,
        "status": "P",
        "week": 3
      },
      {
        "away_franchise_id": 309,
        "away_team_name": "TENNTE",
        "declined_penalties": 0,
        "game": {
          "away_franchise_id": 309,
          "away_team_name": "TENNTE",
          "game_id": 29846,
          "home_franchise_id": 308,
          "home_team_name": "TENNST",
          "player_franchise_id": 308,
          "position": "LG",
          "status": "S",
          "week": 5
        },
        "game_id": 29846,
        "grades_offense": 59.8,
        "grades_offense_penalty": 78.4,
        "grades_pass_block": 48,
        "grades_run_block": 61.6,
        "home_franchise_id": 308,
        "home_team_name": "TENNST",
        "jersey_number": "69",
        "penalties": 0,
        "player_franchise_id": 308,
        "player_id": 172865,
        "position": "LG",
        "snap_counts_pass": 0,
        "snap_counts_pass_block": 30,
        "snap_counts_pass_route": 0,
        "snap_counts_run": 0,
        "snap_counts_run_block": 14,
        "snap_counts_total": 44,
        "snap_counts_total_pass": 30,
        "snap_counts_total_run": 14,
        "status": "S",
        "week": 5
      },
      {
        "away_franchise_id": 308,
        "away_team_name": "TENNST",
        "declined_penalties": 0,
        "game": {
          "away_franchise_id": 308,
          "away_team_name": "TENNST",
          "game_id": 29913,
          "home_franchise_id": 158,
          "home_team_name": "EILLPA",
          "player_franchise_id": 308,
          "position": "LG",
          "status": "S",
          "week": 6
        },
        "game_id": 29913,
        "grades_offense": 49.1,
        "grades_offense_penalty": 76.8,
        "grades_pass_block": 6.2,
        "grades_run_block": 57.4,
        "home_franchise_id": 158,
        "home_team_name": "EILLPA",
        "jersey_number": "69",
        "penalties": 0,
        "player_franchise_id": 308,
        "player_id": 172865,
        "position": "LG",
        "snap_counts_pass": 0,
        "snap_counts_pass_block": 17,
        "snap_counts_pass_route": 0,
        "snap_counts_run": 0,
        "snap_counts_run_block": 12,
        "snap_counts_total": 29,
        "snap_counts_total_pass": 17,
        "snap_counts_total_run": 12,
        "status": "S",
        "week": 6
      },
      {
        "away_franchise_id": 308,
        "away_team_name": "TENNST",
        "declined_penalties": 0,
        "game": {
          "away_franchise_id": 308,
          "away_team_name": "TENNST",
          "game_id": 29986,
          "home_franchise_id": 293,
          "home_team_name": "SEMIZZ",
          "player_franchise_id": 308,
          "position": "LG",
          "status": "S",
          "week": 7
        },
        "game_id": 29986,
        "grades_offense": 53.4,
        "grades_offense_penalty": 79.5,
        "grades_pass_block": 43,
        "grades_run_block": 53.3,
        "home_franchise_id": 293,
        "home_team_name": "SEMIZZ",
        "jersey_number": "69",
        "penalties": 0,
        "player_franchise_id": 308,
        "player_id": 172865,
        "position": "LG",
        "snap_counts_pass": 0,
        "snap_counts_pass_block": 41,
        "snap_counts_pass_route": 0,
        "snap_counts_run": 0,
        "snap_counts_run_block": 19,
        "snap_counts_total": 60,
        "snap_counts_total_pass": 41,
        "snap_counts_total_run": 19,
        "status": "S",
        "week": 7
      },
      {
        "away_franchise_id": 184,
        "away_team_name": "HOWBIS",
        "declined_penalties": 0,
        "game": {
          "away_franchise_id": 184,
          "away_team_name": "HOWBIS",
          "game_id": 30011,
          "home_franchise_id": 308,
          "home_team_name": "TENNST",
          "player_franchise_id": 308,
          "position": "LG",
          "status": "P",
          "week": 8
        },
        "game_id": 30011,
        "grades_offense": 59.9,
        "grades_offense_penalty": 69.8,
        "grades_run_block": 59.8,
        "home_franchise_id": 308,
        "home_team_name": "TENNST",
        "jersey_number": "69",
        "penalties": 0,
        "player_franchise_id": 308,
        "player_id": 172865,
        "position": "LG",
        "snap_counts_pass": 0,
        "snap_counts_pass_block": 0,
        "snap_counts_pass_route": 0,
        "snap_counts_run": 0,
        "snap_counts_run_block": 4,
        "snap_counts_total": 4,
        "snap_counts_total_pass": 0,
        "snap_counts_total_run": 4,
        "status": "P",
        "week": 8
      },
      {
        "away_franchise_id": 308,
        "away_team_name": "TENNST",
        "declined_penalties": 0,
        "game": {
          "away_franchise_id": 308,
          "away_team_name": "TENNST",
          "game_id": 30189,
          "home_franchise_id": 310,
          "home_team_name": "UTMART",
          "player_franchise_id": 308,
          "position": "LG",
          "status": "P",
          "week": 11
        },
        "game_id": 30189,
        "grades_offense": 58,
        "grades_offense_penalty": 75.6,
        "grades_pass_block": 57.4,
        "grades_run_block": 57.3,
        "home_franchise_id": 310,
        "home_team_name": "UTMART",
        "jersey_number": "69",
        "penalties": 0,
        "player_franchise_id": 308,
        "player_id": 172865,
        "position": "LG",
        "snap_counts_pass": 0,
        "snap_counts_pass_block": 18,
        "snap_counts_pass_route": 0,
        "snap_counts_run": 0,
        "snap_counts_run_block": 3,
        "snap_counts_total": 21,
        "snap_counts_total_pass": 18,
        "snap_counts_total_run": 3,
        "status": "P",
        "week": 11
      },
      {
        "away_franchise_id": 171,
        "away_team_name": "GARDNE",
        "declined_penalties": 0,
        "game": {
          "away_franchise_id": 171,
          "away_team_name": "GARDNE",
          "game_id": 30251,
          "home_franchise_id": 308,
          "home_team_name": "TENNST",
          "player_franchise_id": 308,
          "position": "LG",
          "status": "P",
          "week": 12
        },
        "game_id": 30251,
        "grades_offense": 57.9,
        "grades_offense_penalty": 76.5,
        "grades_pass_block": 81.1,
        "grades_run_block": 52.6,
        "home_franchise_id": 308,
        "home_team_name": "TENNST",
        "jersey_number": "69",
        "penalties": 0,
        "player_franchise_id": 308,
        "player_id": 172865,
        "position": "LG",
        "snap_counts_pass": 0,
        "snap_counts_pass_block": 16,
        "snap_counts_pass_route": 0,
        "snap_counts_run": 0,
        "snap_counts_run_block": 9,
        "snap_counts_total": 25,
        "snap_counts_total_pass": 16,
        "snap_counts_total_run": 9,
        "status": "P",
        "week": 12
      }
    ]
  }
}