{
  "candidate_count": 2,
  "match_reason": "exact-name+position+team",
  "resolved_player": {
    "college": null,
    "current_class": "S",
    "current_eligible_year": 2028,
    "dob": null,
    "draft": null,
    "first_name": "BJ",
    "height": 0,
    "id": 170852,
    "jersey_number": "D47",
    "last_name": "Mayes",
    "position": "LB",
    "speed": null,
    "team": {
      "abbreviation": "PURBOI",
      "city": "Purdue",
      "id": 273,
      "nickname": "Boilermakers",
      "primary_color": "#d9c89e",
      "secondary_color": "#000000",
      "slug": "purdue-boilermakers"
    },
    "weight": 205
  }
}